congresslib/__init__.py
congresslib/amendment.py
congresslib/base.py
congresslib/bill.py
congresslib/committee.py
congresslib/communication.py
congresslib/congress.py
congresslib/main.py
congresslib/member.py
congresslib/nomination.py
congresslib/record.py
congresslib/setting.py
congresslib/summary.py
congresslib/treaty.py
congresslib/utils.py
CongressLib-0.1.3.dist-info/LICENSE
CongressLib-0.1.3.dist-info/METADATA
CongressLib-0.1.3.dist-info/WHEEL
CongressLib-0.1.3.dist-info/top_level.txt
CongressLib-0.1.3.dist-info/RECORD
