Metadata-Version: 2.1
Name: CongressLib
Version: 0.1.3
Summary: A Python wrapper for the Congress.gov API.
Author-email: Harry He <zih028@ucsd.edu>
License: MIT
Project-URL: Repository, https://github.com/harryziyuhe/CongressLib
Project-URL: Issues, https://github.com/harryziyuhe/CongressLib/issues
Keywords: Congress,politics,government,legislation
License-File: LICENSE
Requires-Dist: requests
Requires-Dist: python-dotenv
Requires-Dist: typing-extensions
